django_auth_tkt/__init__.py
django_auth_tkt-0.1.0.dist-info/LICENSE.txt
django_auth_tkt-0.1.0.dist-info/METADATA
django_auth_tkt-0.1.0.dist-info/WHEEL
django_auth_tkt-0.1.0.dist-info/top_level.txt
django_auth_tkt-0.1.0.dist-info/RECORD
