Metadata-Version: 2.1
Name: django-auth-tkt
Version: 0.1.0
Summary: Django SSO authentication provider
Home-page: https://github.com/dnknth/django-auth-tkt
Author: dnknth
License: UNKNOWN
Project-URL: Bug Tracker, https://github.com/dnknth/django-auth-tkt/issues
Platform: UNKNOWN
Classifier: Environment :: Web Environment
Classifier: Framework :: Django
Classifier: License :: OSI Approved :: MIT License
Classifier: Operating System :: OS Independent
License-File: LICENSE.txt
Requires-Dist: setuptools
Requires-Dist: auth-tkt (==0.3.*,>=0.3.1)
